{
    "222841664585072641" : {
        "115631038847254535" : {
            "draws" : 0,
            "losses" : 1,
            "wins" : 0
        },
        "118293958072860680" : {
            "draws" : 0,
            "losses" : 1,
            "wins" : 0
        },
        "143576995626745856" : {
            "draws" : 0,
            "losses" : 1,
            "wins" : 0
        },
        "145363035123482624" : {
            "draws" : 0,
            "losses" : 3,
            "wins" : 2
        },
        "154030205806182401" : {
            "draws" : 1,
            "losses" : 0,
            "wins" : 1
        },
        "178478014508564481" : {
            "draws" : 0,
            "losses" : 1,
            "wins" : 0
        },
        "186215130080608256" : {
            "draws" : 0,
            "losses" : 0,
            "wins" : 1
        },
        "197141373604855808" : {
            "draws" : 0,
            "losses" : 3,
            "wins" : 3
        },
        "201424587114676224" : {
            "draws" : 0,
            "losses" : 2,
            "wins" : 0
        },
        "213082110821400578" : {
            "draws" : 1,
            "losses" : 8,
            "wins" : 1
        },
        "221678441664086018" : {
            "draws" : 0,
            "losses" : 1,
            "wins" : 2
        },
        "233118137313132544" : {
            "draws" : 0,
            "losses" : 0,
            "wins" : 3
        },
        "234022797788053504" : {
            "draws" : 0,
            "losses" : 2,
            "wins" : 0
        },
        "269989484597215234" : {
            "draws" : 0,
            "losses" : 0,
            "wins" : 1
        },
        "280944885446475777" : {
            "draws" : 0,
            "losses" : 2,
            "wins" : 13
        },
        "352628918274097153" : {
            "draws" : 0,
            "losses" : 1,
            "wins" : 0
        },
        "405814281767223308" : {
            "draws" : 0,
            "losses" : 1,
            "wins" : 1
        },
        "466741004834439168" : {
            "draws" : 0,
            "losses" : 0,
            "wins" : 1
        },
        "485885339450212353" : {
            "draws" : 0,
            "losses" : 1,
            "wins" : 0
        },
        "98661581855924224" : {
            "draws" : 0,
            "losses" : 1,
            "wins" : 0
        }
    }
}